verbake/__init__.py
verbake/baker.py
verbake-1.0.1.dist-info/METADATA
verbake-1.0.1.dist-info/WHEEL
verbake-1.0.1.dist-info/RECORD
