Metadata-Version: 2.1
Name: verbake
Version: 1.0.1
Summary: Overwrite __version__ in a package's __init__.py with the version from pyproject.toml
Author: Ariff Jeff
Author-email: ariffjeff@icloud.com
Requires-Python: >=3.8,<3.12
Classifier: Programming Language :: Python :: 3
Classifier: Programming Language :: Python :: 3.8
Classifier: Programming Language :: Python :: 3.9
Classifier: Programming Language :: Python :: 3.10
Classifier: Programming Language :: Python :: 3.11
Requires-Dist: packaging (>=23.0,<24.0)
